casased/__init__.py
casased/load.py
casased/notation.py
casased/py.typed
casased/tech.py
casased/utils.py
casased-0.2.2.dist-info/licenses/LICENSE
casased-0.2.2.dist-info/METADATA
casased-0.2.2.dist-info/WHEEL
casased-0.2.2.dist-info/top_level.txt
casased-0.2.2.dist-info/RECORD
