Metadata-Version: 2.4
Name: casased
Version: 0.2.2
Summary: Python library to retrieve historical and intraday data from Casablanca Stock Exchange via Medias24 API with Cloudflare bypass
Home-page: https://github.com/QuantBender/casased
Author: Désiré A. D.
Author-email: desire.dosseh@example.com
License: MIT
Keywords: Web scraping,financial data,casablanca,stock exchange,morocco,MASI
Classifier: Programming Language :: Python :: 3
Classifier: License :: OSI Approved :: MIT License
Classifier: Operating System :: OS Independent
License-File: LICENSE
Requires-Dist: requests
Requires-Dist: beautifulsoup4
Requires-Dist: pandas
Requires-Dist: lxml
Provides-Extra: cloudflare
Requires-Dist: nodriver>=0.30; extra == "cloudflare"
Requires-Dist: seleniumbase>=4.0.0; extra == "cloudflare"
Provides-Extra: browser
Requires-Dist: nodriver>=0.30; extra == "browser"
Requires-Dist: seleniumbase>=4.0.0; extra == "browser"
Dynamic: author
Dynamic: author-email
Dynamic: classifier
Dynamic: description
Dynamic: description-content-type
Dynamic: home-page
Dynamic: keywords
Dynamic: license
Dynamic: license-file
Dynamic: provides-extra
Dynamic: requires-dist
Dynamic: summary
